Workbook
Name _04_Conta_a_Receber: #REF!
Name _04_Conta_a_Receber: #REF!
Name _1: #REF!
Name _1: #REF!
Name _as2: #N/A
Name A: #REF!
Name AAA: #N/A
Name adicional: '[2]Percentual de Impostos'!$D$11
Name ADICIONALEFETIVO: '[2]Percentual de Impostos'!$G$11
Name ano_base: [3]Parâmetros!$F$1
Name AS: #REF!
Name AS: #REF!
Name Atendimento: '[4]00- Premissas'!#REF!
Name Atendimento: '[4]00- Premissas'!#REF!
Name atendimentoano1: '[4]00- Premissas'!$C$4
Name atendimentoano2: '[4]00- Premissas'!$C$5
Name atendimentoano3: '[4]00- Premissas'!$C$6
Name atendimentoano4: '[4]00- Premissas'!$C$7
Name atendimentoano5: '[4]00- Premissas'!$C$8
Name aumentofolha: '[4]00- Premissas'!$C$11
Name aumentopreços: '[4]00- Premissas'!#REF!
Name aumentopreços: '[4]00- Premissas'!#REF!
Name Banco: #REF!
Name Banco: #REF!
Name Bancos: #REF!
Name Bancos: #REF!
Name CAIXA: [5]BASE!$B$3:$B$7
Name CATEGORIAS: #REF!
Name CATEGORIAS: #REF!
Name CFATAC: '[6]Custo Financeiro'!$D$36
Name Choices_Wrapper: #N/A
Name CMV: '[2]Volume de Vendas'!$I$5
Name COFINS: '[2]Percentual de Impostos'!$D$8
Name comatac: '[7]Despesas Variáveis'!$E$5
Name comissão: [2]Comissões!$D$20
Name comissãogerente: '[4]00- Premissas'!$C$19
Name comissoes: [8]Premissas!#REF!
Name comissoes: #REF!
Name Comissões: '[4]00- Premissas'!$C$18
Name contaempresa: [8]Premissas!#REF!
Name contaempresa: #REF!
Name contaroberta: [8]Premissas!#REF!
Name contaroberta: #REF!
Name CONTAS: #REF!
Name CONTAS: [5]Realizado!$B$14:$B$102
Name CSEFETIVO: '[2]Percentual de Impostos'!$G$12
Name CSLL: '[2]Percentual de Impostos'!$D$12
Name CUSTOAPOLICE: [9]Parâmetros!$C$13
Name CustoMP: #REF!
Name CustoMP: #REF!
Name D: '[10]Base de Dados'!$B$18:$B$21
Name D: '[11]Base de Dados'!$B$18:$B$21
Name Dashboard: '[12]Custo Financeiro'!$D$36
Name ddd: [13]BASE!$B$3:$B$8
Name dddddd: [14]Realizado!$B$14:$B$102
Name DESPCASA: [8]Premissas!#REF!
Name DESPCASA: #REF!
Name Despesas: [8]Premissas!#REF!
Name Despesas: #REF!
Name devoluções: '[4]00- Premissas'!#REF!

Sheet DRE
D1: Mês/Ano
B2: DRE | D2: ='Dados Mov Financeira'!A2&"/"&'Dados Mov Financeira'!B2 -> /
D3: R$ | E3: %
D4: REALIZADO
B5: RECEITA OPERACIONAL BRUTA | D5: =SUM(D6:D7) -> 0 | E5: =IFERROR(D5/D$5,0) -> 0
B6: Recebimento dos serviços prestados | D6: =SUMIFS('Dados Mov Financeira'!$N:$N,'Dados Mov Financeira'!$O:$O,DRE!$B6) -> 0 | E6: =IFERROR(D6/D$5,0) -> 0
B7: Recebimento de Outras receitas | D7: =SUMIFS('Dados Mov Financeira'!$N:$N,'Dados Mov Financeira'!$O:$O,DRE!$B7) -> 0 | E7: =IFERROR(D7/D$5,0) -> 0
B9: (-) DEDUÇÕES | D9: =D10+D15 -> 0 | E9: =IFERROR(D9/D$5,0) -> 0
B10: Devoluções e Cancelamentos | D10: =SUM(D11:D14) -> 0 | E10: =IFERROR(D10/D$5,0) -> 0
B11: (-) Cheques Devolvidos | D11: =SUMIFS('Dados Mov Financeira'!$N:$N,'Dados Mov Financeira'!$O:$O,DRE!$B11) -> 0 | E11: =IFERROR(D11/D$5,0) -> 0
B12: (-) Créditos Perdidos | D12: =SUMIFS('Dados Mov Financeira'!$N:$N,'Dados Mov Financeira'!$O:$O,DRE!$B12) -> 0 | E12: =IFERROR(D12/D$5,0) -> 0
B13: (-) Devoluções a Clientes | D13: =SUMIFS('Dados Mov Financeira'!$N:$N,'Dados Mov Financeira'!$O:$O,DRE!$B13) -> 0 | E13: =IFERROR(D13/D$5,0) -> 0
B14: (-) Cancelamento de Vendas | D14: =SUMIFS('Dados Mov Financeira'!$N:$N,'Dados Mov Financeira'!$O:$O,DRE!$B14) -> 0 | E14: =IFERROR(D14/D$5,0) -> 0
B15: Impostos | D15: =SUMIFS('Dados Mov Financeira'!$N:$N,'Dados Mov Financeira'!$O:$O,DRE!$B15) -> 0 | E15: =IFERROR(D15/D$5,0) -> 0
B16: (-) Darf Cofins | D16: =SUMIFS('Dados Mov Financeira'!$N:$N,'Dados Mov Financeira'!$O:$O,DRE!$B16) -> 0 | E16: =IFERROR(D16/D$5,0) -> 0
B17: (-) Darf Pis | D17: =SUMIFS('Dados Mov Financeira'!$N:$N,'Dados Mov Financeira'!$O:$O,DRE!$B17) -> 0 | E17: =IFERROR(D17/D$5,0) -> 0
B18: (-) Das Simples Nacional | D18: =SUMIFS('Dados Mov Financeira'!$N:$N,'Dados Mov Financeira'!$O:$O,DRE!$B18) -> 0 | E18: =IFERROR(D18/D$5,0) -> 0
B19: (-) Issqn Prefeitura | D19: =SUMIFS('Dados Mov Financeira'!$N:$N,'Dados Mov Financeira'!$O:$O,DRE!$B19) -> 0 | E19: =IFERROR(D19/D$5,0) -> 0
B21: RECEITA OPERACIONAL LÍQUIDA | D21: =D5+D9 -> 0 | E21: =IFERROR(D21/D$5,0) -> 0
B23: (-) CUSTOS | D23: =SUM(D24,D29) -> 0 | E23: =IFERROR(D23/D$5,0) -> 0
B24: (-) Custos Dos Materiais | D24: =SUM(D25:D28) -> 0 | E24: =IFERROR(D24/D$5,0) -> 0
B25: (-) Compras De Materiais (consumo) | D25: =SUMIFS('Dados Mov Financeira'!$N:$N,'Dados Mov Financeira'!$O:$O,DRE!$B25) -> 0 | E25: =IFERROR(D25/D$5,0) -> 0
B26: (-) Compras De Materiais (revenda) | D26: =SUMIFS('Dados Mov Financeira'!$N:$N,'Dados Mov Financeira'!$O:$O,DRE!$B26) -> 0 | E26: =IFERROR(D26/D$5,0) -> 0
B27: (-) Exames - Laboratório | D27: =SUMIFS('Dados Mov Financeira'!$N:$N,'Dados Mov Financeira'!$O:$O,DRE!$B27) -> 0 | E27: =IFERROR(D27/D$5,0) -> 0
B28: (-) Fretes Sobre Compras | D28: =SUMIFS('Dados Mov Financeira'!$N:$N,'Dados Mov Financeira'!$O:$O,DRE!$B28) -> 0 | E28: =IFERROR(D28/D$5,0) -> 0
B29: (-) Custos Da Mão-de-obra Direta | D29: =SUMIFS('Dados Mov Financeira'!$N:$N,'Dados Mov Financeira'!$O:$O,DRE!$B29) -> 0 | E29: =IFERROR(D29/D$5,0) -> 0
B30: (-) Salários Dos Veterinários | D30: =SUMIFS('Dados Mov Financeira'!$N:$N,'Dados Mov Financeira'!$O:$O,DRE!$B30) -> 0 | E30: =IFERROR(D30/D$5,0) -> 0
B32: LUCRO BRUTO | D32: =SUM(D21,D23) -> 0 | E32: =IFERROR(D32/D$5,0) -> 0
B34: (-) Despesas Variáveis | D34: =SUM(D35) -> 0 | E34: =IFERROR(D34/D$5,0) -> 0
B35: (-) Despesas Comerciais | D35: =SUM(D36:D39) -> 0 | E35: =IFERROR(D35/D$5,0) -> 0
B36: (-) Bonificação | D36: =SUMIFS('Dados Mov Financeira'!$N:$N,'Dados Mov Financeira'!$O:$O,DRE!$B36) -> 0 | E36: =IFERROR(D36/D$5,0) -> 0
B37: (-) Royalties | D37: =SUMIFS('Dados Mov Financeira'!$N:$N,'Dados Mov Financeira'!$O:$O,DRE!$B37) -> 0 | E37: =IFERROR(D37/D$5,0) -> 0
B38: (-) Fundo Nacional de Propaganda | D38: =SUMIFS('Dados Mov Financeira'!$N:$N,'Dados Mov Financeira'!$O:$O,DRE!$B38) -> 0 | E38: =IFERROR(D38/D$5,0) -> 0
B39: (-) Marketing E Propaganda | D39: =SUMIFS('Dados Mov Financeira'!$N:$N,'Dados Mov Financeira'!$O:$O,DRE!$B39) -> 0 | E39: =IFERROR(D39/D$5,0) -> 0
B42: MARGEM DE CONTRIBUIÇÃO | D42: =SUM(D32,D34) -> 0 | E42: =IFERROR(D42/D$5,0) -> 0
B44: (-) DESPESAS FIXAS | D44: =SUM(D45,D70,D85,D89) -> 0 | E44: =IFERROR(D44/D$5,0) -> 0
B45: (-) Despesas Administrativas | D45: =SUM(D46:D69) -> 0 | E45: =IFERROR(D45/D$5,0) -> 0
B46: (-) Aluguel | D46: =SUMIFS('Dados Mov Financeira'!$N:$N,'Dados Mov Financeira'!$O:$O,DRE!$B46) -> 0 | E46: =IFERROR(D46/D$45,0) -> 0
B47: (-) Brindes / Prêmios | D47: =SUMIFS('Dados Mov Financeira'!$N:$N,'Dados Mov Financeira'!$O:$O,DRE!$B47) -> 0 | E47: =IFERROR(D47/D$45,0) -> 0
B48: (-) Cartórios E Protestos | D48: =SUMIFS('Dados Mov Financeira'!$N:$N,'Dados Mov Financeira'!$O:$O,DRE!$B48) -> 0 | E48: =IFERROR(D48/D$45,0) -> 0
B49: (-) Confraternizações | D49: =SUMIFS('Dados Mov Financeira'!$N:$N,'Dados Mov Financeira'!$O:$O,DRE!$B49) -> 0 | E49: =IFERROR(D49/D$45,0) -> 0
B50: (-) Consultorias | D50: =SUMIFS('Dados Mov Financeira'!$N:$N,'Dados Mov Financeira'!$O:$O,DRE!$B50) -> 0 | E50: =IFERROR(D50/D$45,0) -> 0
B51: (-) Contador | D51: =SUMIFS('Dados Mov Financeira'!$N:$N,'Dados Mov Financeira'!$O:$O,DRE!$B51) -> 0 | E51: =IFERROR(D51/D$45,0) -> 0
B52: (-) Estacionamento | D52: =SUMIFS('Dados Mov Financeira'!$N:$N,'Dados Mov Financeira'!$O:$O,DRE!$B52) -> 0 | E52: =IFERROR(D52/D$45,0) -> 0
B53: (-) Correio | D53: =SUMIFS('Dados Mov Financeira'!$N:$N,'Dados Mov Financeira'!$O:$O,DRE!$B53) -> 0 | E53: =IFERROR(D53/D$45,0) -> 0
B54: (-) Honorários De Advogados | D54: =SUMIFS('Dados Mov Financeira'!$N:$N,'Dados Mov Financeira'!$O:$O,DRE!$B54) -> 0 | E54: =IFERROR(D54/D$45,0) -> 0
B55: (-) Impressos E Materiais Gráficos | D55: =SUMIFS('Dados Mov Financeira'!$N:$N,'Dados Mov Financeira'!$O:$O,DRE!$B55) -> 0 | E55: =IFERROR(D55/D$45,0) -> 0
B56: (-) Internet | D56: =SUMIFS('Dados Mov Financeira'!$N:$N,'Dados Mov Financeira'!$O:$O,DRE!$B56) -> 0 | E56: =IFERROR(D56/D$45,0) -> 0
B57: (-) Lanches E Refeições | D57: =SUMIFS('Dados Mov Financeira'!$N:$N,'Dados Mov Financeira'!$O:$O,DRE!$B57) -> 0 | E57: =IFERROR(D57/D$45,0) -> 0
... B69: (-) Telefone Celular | D69: =SUMIFS('Dados Mov Financeira'!$N:$N,'Dados Mov Financeira'!$O:$O,DRE!$B69) -> 0 | E69: =IFERROR(D69/D$45,0) -> 0
B70: (-) Despesas Com Pessoal | D70: =SUM(D71:D84) -> 0 | E70: =IFERROR(D70/D$5,0) -> 0
B71: (-) 13 Salario | D71: =SUMIFS('Dados Mov Financeira'!$N:$N,'Dados Mov Financeira'!$O:$O,DRE!$B71) -> 0 | E71: =IFERROR(D71/D$5,0) -> 0
B72: (-) Cursos E Treinamentos | D72: =SUMIFS('Dados Mov Financeira'!$N:$N,'Dados Mov Financeira'!$O:$O,DRE!$B72) -> 0 | E72: =IFERROR(D72/D$5,0) -> 0
B73: (-) Exame Ocupacional | D73: =SUMIFS('Dados Mov Financeira'!$N:$N,'Dados Mov Financeira'!$O:$O,DRE!$B73) -> 0 | E73: =IFERROR(D73/D$5,0) -> 0
B74: (-) Férias | D74: =SUMIFS('Dados Mov Financeira'!$N:$N,'Dados Mov Financeira'!$O:$O,DRE!$B74) -> 0 | E74: =IFERROR(D74/D$5,0) -> 0
B75: (-) Gps Inss | D75: =SUMIFS('Dados Mov Financeira'!$N:$N,'Dados Mov Financeira'!$O:$O,DRE!$B75) -> 0 | E75: =IFERROR(D75/D$5,0) -> 0
B76: (-) Plano De Saúde | D76: =SUMIFS('Dados Mov Financeira'!$N:$N,'Dados Mov Financeira'!$O:$O,DRE!$B76) -> 0 | E76: =IFERROR(D76/D$5,0) -> 0
B77: (-) Prêmios Por Produtividade (funcionários) | D77: =SUMIFS('Dados Mov Financeira'!$N:$N,'Dados Mov Financeira'!$O:$O,DRE!$B77) -> 0 | E77: =IFERROR(D77/D$5,0) -> 0
B78: (-) Rescisões | D78: =SUMIFS('Dados Mov Financeira'!$N:$N,'Dados Mov Financeira'!$O:$O,DRE!$B78) -> 0 | E78: =IFERROR(D78/D$5,0) -> 0
B79: (-) Salários Dos Funcionários | D79: =SUMIFS('Dados Mov Financeira'!$N:$N,'Dados Mov Financeira'!$O:$O,DRE!$B79) -> 0 | E79: =IFERROR(D79/D$5,0) -> 0
B80: (-) Uniformes | D80: =SUMIFS('Dados Mov Financeira'!$N:$N,'Dados Mov Financeira'!$O:$O,DRE!$B80) -> 0 | E80: =IFERROR(D80/D$5,0) -> 0
B81: (-) Vale Alimentação | D81: =SUMIFS('Dados Mov Financeira'!$N:$N,'Dados Mov Financeira'!$O:$O,DRE!$B81) -> 0 | E81: =IFERROR(D81/D$5,0) -> 0
B82: (-) Vale Transporte | D82: =SUMIFS('Dados Mov Financeira'!$N:$N,'Dados Mov Financeira'!$O:$O,DRE!$B82) -> 0 | E82: =IFERROR(D82/D$5,0) -> 0
... B84: (-) Fgts | D84: =SUMIFS('Dados Mov Financeira'!$N:$N,'Dados Mov Financeira'!$O:$O,DRE!$B84) -> 0 | E84: =IFERROR(D84/D$5,0) -> 0
B85: (-) Gastos Gerais Nos Serviços | D85: =SUM(D86:D88) -> 0 | E85: =IFERROR(D85/D$5,0) -> 0
B86: (-) Água E Esgoto | D86: =SUMIFS('Dados Mov Financeira'!$N:$N,'Dados Mov Financeira'!$O:$O,DRE!$B86) -> 0 | E86: =IFERROR(D86/D$5,0) -> 0
B87: (-) Energia Elétrica | D87: =SUMIFS('Dados Mov Financeira'!$N:$N,'Dados Mov Financeira'!$O:$O,DRE!$B87) -> 0 | E87: =IFERROR(D87/D$5,0) -> 0
B88: (-) Manutenção De Equipamentos | D88: =SUMIFS('Dados Mov Financeira'!$N:$N,'Dados Mov Financeira'!$O:$O,DRE!$B88) -> 0 | E88: =IFERROR(D88/D$5,0) -> 0
B89: (-) Despesas Tributárias | D89: =SUM(D90:D102) -> 0 | E89: =IFERROR(D89/D$5,0) -> 0
B90: (-) Contribuições Sindicais | D90: =SUMIFS('Dados Mov Financeira'!$N:$N,'Dados Mov Financeira'!$O:$O,DRE!$B90) -> 0 | E90: =IFERROR(D90/D$5,0) -> 0
B91: (-) Darf Contribuição Social - Csll | D91: =SUMIFS('Dados Mov Financeira'!$N:$N,'Dados Mov Financeira'!$O:$O,DRE!$B91) -> 0 | E91: =IFERROR(D91/D$5,0) -> 0
B92: (-) Darf Imposto De Renda - Irpj | D92: =SUMIFS('Dados Mov Financeira'!$N:$N,'Dados Mov Financeira'!$O:$O,DRE!$B92) -> 0 | E92: =IFERROR(D92/D$5,0) -> 0
B93: (-) Darf Irrf Sobre Aluguel/salários/outros | D93: =SUMIFS('Dados Mov Financeira'!$N:$N,'Dados Mov Financeira'!$O:$O,DRE!$B93) -> 0 | E93: =IFERROR(D93/D$5,0) -> 0
B94: (-) Impostos E Taxas | D94: =SUMIFS('Dados Mov Financeira'!$N:$N,'Dados Mov Financeira'!$O:$O,DRE!$B94) -> 0 | E94: =IFERROR(D94/D$5,0) -> 0
B95: (-) Iof | D95: =SUMIFS('Dados Mov Financeira'!$N:$N,'Dados Mov Financeira'!$O:$O,DRE!$B95) -> 0 | E95: =IFERROR(D95/D$5,0) -> 0
B96: (-) Iptu | D96: =SUMIFS('Dados Mov Financeira'!$N:$N,'Dados Mov Financeira'!$O:$O,DRE!$B96) -> 0 | E96: =IFERROR(D96/D$5,0) -> 0
B97: (-) Despesas Financeiras | D97: =SUM(D98:D102) -> 0 | E97: =IFERROR(D97/D$5,0) -> 0
B98: (-) Despesas Bancárias | D98: =SUMIFS('Dados Mov Financeira'!$N:$N,'Dados Mov Financeira'!$O:$O,DRE!$B98) -> 0 | E98: =IFERROR(D98/D$5,0) -> 0
B99: (-) Juros Pagos A Fornecedores | D99: =SUMIFS('Dados Mov Financeira'!$N:$N,'Dados Mov Financeira'!$O:$O,DRE!$B99) -> 0 | E99: =IFERROR(D99/D$5,0) -> 0
B100: (-) Juros Sobre Descontos Cheques/duplicatas/cartões | D100: =SUMIFS('Dados Mov Financeira'!$N:$N,'Dados Mov Financeira'!$O:$O,DRE!$B100) -> 0 | E100: =IFERROR(D100/D$5,0) -> 0
B101: (-) Taxas De Boletos Bancários | D101: =SUMIFS('Dados Mov Financeira'!$N:$N,'Dados Mov Financeira'!$O:$O,DRE!$B101) -> 0 | E101: =IFERROR(D101/D$5,0) -> 0
B102: (-) Taxa Administração Cartão Débito Ou Crédito | D102: =SUMIFS('Dados Mov Financeira'!$N:$N,'Dados Mov Financeira'!$O:$O,DRE!$B102) -> 0 | E102: =IFERROR(D102/D$5,0) -> 0
B104: EBTIDA | D104: =D42+D44 -> 0 | E104: =IFERROR(D104/D$5,0) -> 0
B106: RESULTADO FINANCEIRO | D106: =D107+D110 -> 0 | E106: =IFERROR(D106/D$5,0) -> 0
B107: (-) Despesas Financeiras | D107: =SUM(D108:D109) -> 0 | E107: =IFERROR(D107/D$5,0) -> 0
B108: (-) Juros De Financiamentos | D108: =SUMIFS('Dados Mov Financeira'!$N:$N,'Dados Mov Financeira'!$O:$O,DRE!$B108) -> 0 | E108: =IFERROR(D108/D$5,0) -> 0
B109: (-) Aplicações Financeiras | D109: =SUMIFS('Dados Mov Financeira'!$N:$N,'Dados Mov Financeira'!$O:$O,DRE!$B109) -> 0 | E109: =IFERROR(D109/D$5,0) -> 0
B110: Receitas Financeiras | D110: =SUMIFS('Dados Mov Financeira'!$N:$N,'Dados Mov Financeira'!$O:$O,DRE!$B110) -> 0 | E110: =IFERROR(D110/D$5,0) -> 0
B111: Descontos Obtidos | D111: =SUMIFS('Dados Mov Financeira'!$N:$N,'Dados Mov Financeira'!$O:$O,DRE!$B111) -> 0 | E111: =IFERROR(D111/D$5,0) -> 0
B112: Juros De Aplicações Financeiras | D112: =SUMIFS('Dados Mov Financeira'!$N:$N,'Dados Mov Financeira'!$O:$O,DRE!$B112) -> 0 | E112: =IFERROR(D112/D$5,0) -> 0
B113: Juros/multas Recebidos | D113: =SUMIFS('Dados Mov Financeira'!$N:$N,'Dados Mov Financeira'!$O:$O,DRE!$B113) -> 0 | E113: =IFERROR(D113/D$5,0) -> 0
B115: LUCRO OPERACIONAL | D115: =D104+D106 -> 0 | E115: =IFERROR(D115/D$5,0) -> 0
B117: Extra Operacional | D117: =SUM(D118:D128) -> 0 | E117: =IFERROR(D117/D$5,0) -> 0
B118: (-) Benfeitoria Em Imóveis De Terceiros | D118: =SUMIFS('Dados Mov Financeira'!$N:$N,'Dados Mov Financeira'!$O:$O,DRE!$B118) -> 0 | E118: =IFERROR(D118/D$5,0) -> 0
B119: (-) Imóveis | D119: =SUMIFS('Dados Mov Financeira'!$N:$N,'Dados Mov Financeira'!$O:$O,DRE!$B119) -> 0 | E119: =IFERROR(D119/D$5,0) -> 0
B120: (-) Equipamentos De Informática | D120: =SUMIFS('Dados Mov Financeira'!$N:$N,'Dados Mov Financeira'!$O:$O,DRE!$B120) -> 0 | E120: =IFERROR(D120/D$5,0) -> 0
B121: (-) Maquinas E Equipamentos | D121: =SUMIFS('Dados Mov Financeira'!$N:$N,'Dados Mov Financeira'!$O:$O,DRE!$B121) -> 0 | E121: =IFERROR(D121/D$5,0) -> 0
B122: (-) Móveis E Utensílios | D122: =SUMIFS('Dados Mov Financeira'!$N:$N,'Dados Mov Financeira'!$O:$O,DRE!$B122) -> 0 | E122: =IFERROR(D122/D$5,0) -> 0
B123: (-) Empréstimos De Capital De Giro | D123: =SUMIFS('Dados Mov Financeira'!$N:$N,'Dados Mov Financeira'!$O:$O,DRE!$B123) -> 0 | E123: =IFERROR(D123/D$5,0) -> 0
B124: (-) Financiamentos | D124: =SUMIFS('Dados Mov Financeira'!$N:$N,'Dados Mov Financeira'!$O:$O,DRE!$B124) -> 0 | E124: =IFERROR(D124/D$5,0) -> 0
...

Sheet Dados Mov Financeira
A1: Mês | B1: Ano | C1: data | D1: cob - CATEGORIA | E1: DESCRIÇÃO | F1: FORNECEDOR | H1: ITEM | I1: CENTRO CUSTO | K1: l | L1: DEBITO | M1: CREDITO | N1: D-C | O1: Grupo de conta

Sheet Grupos de Contas
A2: RECEITA OPERACIONAL BRUTA
A3: Faturamento dos serviços prestados
A4: Outras receitas
A5: Recebimento de Outras receitas
A6: Recebimento dos serviços prestados
A8: (-) DEDUÇÕES
A9: Devoluções e Cancelamentos
A10: (-) Cheques Devolvidos
A11: (-) Créditos Perdidos
A12: (-) Devoluções a Clientes
A13: (-) Cancelamento de Vendas
A14: Impostos
... A133: Outras receitas da empresa
